tests/__init__.py
youtube_dl_scraper/__init__.py
youtube_dl_scraper/version.py
youtube_dl_scraper/converter/__init__.py
youtube_dl_scraper/converter/audio_converter.py
youtube_dl_scraper/converter/base_converter.py
youtube_dl_scraper/converter/video_converter.py
youtube_dl_scraper/core/__init__.py
youtube_dl_scraper/core/base_scraper.py
youtube_dl_scraper/core/caption.py
youtube_dl_scraper/core/caption_array.py
youtube_dl_scraper/core/exceptions.py
youtube_dl_scraper/core/scraper_manager.py
youtube_dl_scraper/core/stream.py
youtube_dl_scraper/core/stream_array.py
youtube_dl_scraper/core/video.py
youtube_dl_scraper/core/youtube.py
youtube_dl_scraper/site_scrapers/__init__.py
youtube_dl_scraper/site_scrapers/caption_scrapers/__init__.py
youtube_dl_scraper/site_scrapers/caption_scrapers/downsub.py
youtube_dl_scraper/site_scrapers/video_scrapers/__init__.py
youtube_dl_scraper/site_scrapers/video_scrapers/savetube.py
youtube_dl_scraper/site_scrapers/video_scrapers/y2save.py
youtube_dl_scraper/utils/__init__.py
youtube_dl_scraper/utils/extract_video_id.py
youtube_dl_scraper/utils/filename_extractor.py
youtube_dl_scraper/utils/format_time.py
youtube_dl_scraper/utils/playwright_runner.py
youtube_dl_scraper/utils/registration.py
youtube_dl_scraper/utils/title_to_slug.py
youtube_dl_scraper-0.0.0a1.dist-info/LICENSE
youtube_dl_scraper-0.0.0a1.dist-info/METADATA
youtube_dl_scraper-0.0.0a1.dist-info/WHEEL
youtube_dl_scraper-0.0.0a1.dist-info/top_level.txt
youtube_dl_scraper-0.0.0a1.dist-info/zip-safe
youtube_dl_scraper-0.0.0a1.dist-info/RECORD
