Metadata-Version: 2.1
Name: youtube_dl_scraper
Version: 0.0.0a1
Summary: Python 3 library for downloading YouTube Videos.
Home-page: https://github.com/DannyAkintunde/Youtube-dl-scraper/tree/dev
Author: Daniel Akintunde
Author-email: dan29july@gmail.com
License: MIT
Project-URL: Bug Reports, https://github.com/DannyAkintunde/Youtube-dl-scraper/issues
Keywords: youtube,download,video,stream
Classifier: Development Status :: 1 - Planning
Classifier: Intended Audience :: Developers
Classifier: Natural Language :: English
Classifier: Operating System :: OS Independent
Classifier: Programming Language :: Python :: 3.7
Classifier: Programming Language :: Python :: 3.8
Classifier: Programming Language :: Python :: 3.9
Classifier: Programming Language :: Python :: 3.10
Classifier: Programming Language :: Python :: 3.11
Classifier: Programming Language :: Python
Classifier: License :: OSI Approved :: MIT License
Classifier: Topic :: Internet
Classifier: Topic :: Multimedia :: Video
Classifier: Topic :: Software Development :: Libraries :: Python Modules
Classifier: Topic :: Utilities
Requires-Python: >=3.7
License-File: LICENSE
Requires-Dist: requests
Requires-Dist: fake-useragent
Requires-Dist: ffmpeg-python
Requires-Dist: fleep
Requires-Dist: langcodes
Requires-Dist: tqdm
Requires-Dist: Unidecode
